try_work_files/__init__.py
try_work_files/try_work_files
try_work_files-0.0.7.dist-info/METADATA
try_work_files-0.0.7.dist-info/WHEEL
try_work_files-0.0.7.dist-info/RECORD
