Metadata-Version: 2.4
Name: try-work-files
Version: 0.0.7
Summary: try-work-files
License: BSD-3-Clause
Author: FH
Author-email: hiroshifuu@outlook.com
Requires-Python: >=3.8,<4.0
Classifier: Development Status :: 4 - Beta
Classifier: Environment :: Web Environment
Classifier: Intended Audience :: Developers
Classifier: License :: OSI Approved :: BSD License
Classifier: Operating System :: OS Independent
Classifier: Programming Language :: Python
Classifier: Programming Language :: Python :: 3
Classifier: Programming Language :: Python :: 3.8
Classifier: Programming Language :: Python :: 3.9
Classifier: Programming Language :: Python :: 3.10
Classifier: Programming Language :: Python :: 3.11
Classifier: Programming Language :: Python :: 3.12
Classifier: Programming Language :: Python :: 3.13
Classifier: Programming Language :: Python :: 3.14
Classifier: Topic :: Software Development :: Libraries :: Python Modules
Project-URL: Documentation, https://github.com/HiroshiFuu/try-work-files/blob/master/README.md
Project-URL: Homepage, https://github.com/HiroshiFuu/try-work-files
Project-URL: Repository, https://github.com/HiroshiFuu/try-work-files
